Workbook
Name CD: #REF!
Name PRACTICAS: #REF!

Sheet TODOS
A1: nOrden | B1: dFecha | C1: sPaciente | D1: nEdad | E1: sSexo | F1: sEntidad | G1: sNroAfiliado | H1: sBono | I1: sEstado | J1: sTipoPaciente | K1: sSubPlan | L1: sPlan | M1: sCliente | N1: sServicio | O1: sEmpresa | P1: sFilial | Q1: lGuardia | R1: sClase | S1: sPrestacion | T1: sNombrePrestacion | U1: sRegion | V1: nCantidad | W1: sProfesionalDeriv | X1: sProfesionalControlador | Y1: sProfesionalEjec | Z1: nHonorarios | AA1: nGastos | AB1: nDrogas | AC1: nCopago | AD1: sSet | AE1: sAltaUsuario | AF1: sObsEstado | AG1: nSaldo | AH1: sHora | AI1: dFechaEntrega
A2: 995667 | B2: 46143 | C2: PEREZ, EULALIA | D2: 86 | E2: F | F2: PAMI INT CC | G2: 150357314001100 | I2: Lista para Facturar | J2: Exento | K2: UNICO | L2: 1 | N2: RADIOLOGIA | O2: DIAGNOSR | P2: CLINIC - CLINICA CIUDAD | Q2: NO | R2: NNM | S2: 340301 | T2: RX DE TORAX | U2: SIN REGION | V2: 1 | W2: VILLARROEL, OSCAR | X2: 0 | Y2: VARELA, JULIO | Z2: 0 | AA2: 0 | AB2: 0 | AC2: 0 | AD2: S/S | AE2: PMARTIN | AF2: Proceso Auto: Recalculo Orden | AG2: 0 | AH2: 0.0013888889 | AI2: 46147
A3: 995668 | B3: 46143 | C3: SALAS, ALEXANDER | D3: 15 | E3: M | F3: H REGIONAL MG | G3: 50513771 | I3: Lista para Facturar | J3: Exento | K3: UNICO | L3: 1 | N3: TOMOGRAFIA | O3: DIAGNOSR | P3: MALARG - MALARGUE | Q3: NO | R3: NNM | S3: 922026 | T3: TOMOGRAFIA COMPUTADA MULTICORT | U3: SIN REGION | V3: 2 | W3: ARANCIBIA, FERNANDO | X3: 0 | Y3: ASIGNADO, POR RIS | Z3: 0 | AA3: 0 | AB3: 0 | AC3: 0 | AD3: S/S | AE3: VJAQUE | AG3: 0 | AH3: 0.86527778 | AI3: 46147
A4: 995669 | B4: 46144 | C4: NUÑEZ, ELIDE | D4: 85 | E4: F | F4: PAMI AMB CC | G4: 150179740308/00 | I4: Lista para Facturar | J4: Exento | K4: UNICO | L4: 1 | N4: TOMOGRAFIA | O4: DIAGNOSR | P4: DIAGNOSR - CENTRO DEL DIAGNOSTICO | Q4: NO | R4: NNM | S4: 341001 | T4: TOMOGRAFIA COMPUTADA CEREBRAL | U4: SIN REGION | V4: 1 | W4: BARCUDI, DARIO | X4: 0 | Y4: ASIGNADO, POR RIS | Z4: 0 | AA4: 0 | AB4: 0 | AC4: 0 | AD4: S/S | AE4: ELUCERO | AG4: 0 | AH4: 0.34097222 | AI4: 46148
A5: 995670 | B5: 46144 | C5: OLANO, JULIO ROBERTO | D5: 70 | E5: M | F5: PAMI AMB CC | G5: 150086028908/00 | I5: Lista para Facturar | J5: Exento | K5: UNICO | L5: 1 | N5: RADIOLOGIA | O5: DIAGNOSR | P5: DIAGNOSR - CENTRO DEL DIAGNOSTICO | Q5: NO | R5: NNM | S5: 340222 | T5: ESPINOGRAMA | U5: SIN REGION | V5: 1 | W5: PEREZ, JOSE LUIS | X5: 0 | Y5: VARELA, JULIO | Z5: 0 | AA5: 0 | AB5: 0 | AC5: 0 | AD5: S/S | AE5: ELUCERO | AG5: 0 | AH5: 0.34652778 | AI5: 46148
A6: 995671 | B6: 46144 | C6: LOPEZ, MARIA ESTHER | D6: 64 | E6: F | F6: PAMI AMB CC | G6: 155938567106/00 | I6: Lista para Facturar | J6: Exento | K6: UNICO | L6: 1 | N6: RADIOLOGIA | O6: DIAGNOSR | P6: DIAGNOSR - CENTRO DEL DIAGNOSTICO | Q6: NO | R6: NNM | S6: 340201 | T6: RX CRANEO CARA SENOS PAR. 1EXP | U6: SIN REGION | V6: 1 | W6: PEREZ, JOSE LUIS | X6: 0 | Y6: VARELA, JULIO | Z6: 0 | AA6: 0 | AB6: 0 | AC6: 0 | AD6: S/S | AE6: ELUCERO | AG6: 0 | AH6: 0.35069444 | AI6: 46148
A7: 995671 | B7: 46144 | C7: LOPEZ, MARIA ESTHER | D7: 64 | E7: F | F7: PAMI AMB CC | G7: 155938567106/00 | I7: Lista para Facturar | J7: Exento | K7: UNICO | L7: 1 | N7: RADIOLOGIA | O7: DIAGNOSR | P7: DIAGNOSR - CENTRO DEL DIAGNOSTICO | Q7: NO | R7: NNM | S7: 340202 | T7: RX CRANEO CARA SENOS PAR.SUBS | U7: SIN REGION | V7: 1 | W7: PEREZ, JOSE LUIS | X7: 0 | Y7: VARELA, JULIO | Z7: 0 | AA7: 0 | AB7: 0 | AC7: 0 | AD7: S/S | AE7: ELUCERO | AG7: 0 | AH7: 0.35069444 | AI7: 46148
A8: 995672 | B8: 46144 | C8: SAVARINO RUSSO, MARTIN | D8: 23 | E8: M | F8: SANCOR SALUD | G8: 870049/02 | I8: Lista para Facturar | J8: Exento | K8: CMSR CD RX-TAC 61037/0 | L8: 1 | N8: RESONANCIA | O8: DIAGNOSR | P8: DIAGNOSR - CENTRO DEL DIAGNOSTICO | Q8: NO | R8: NNM | S8: 460275 | T8: RMI-AC RODILLA | U8: SIN REGION | V8: 1 | W8: CAMILLETTI, MARIANO | X8: 0 | Y8: ASIGNADO, POR RIS | Z8: 0 | AA8: 0 | AB8: 0 | AC8: 0 | AD8: S/S | AE8: ELUCERO | AG8: 0 | AH8: 0.35277778 | AI8: 46148
A9: 995673 | B9: 46144 | C9: MONTAÑA, MARCOS RAFAEL | D9: 69 | E9: M | F9: PAMI AMB CC | G9: 465017853704/00 | I9: Lista para Facturar | J9: Exento | K9: UNICO | L9: 1 | N9: RADIOLOGIA | O9: DIAGNOSR | P9: DIAGNOSR - CENTRO DEL DIAGNOSTICO | Q9: NO | R9: NNM | S9: 340222 | T9: ESPINOGRAMA | U9: SIN REGION | V9: 1 | W9: OVIEDO, JORGE EDUARDO | X9: 0 | Y9: VARELA, JULIO | Z9: 0 | AA9: 0 | AB9: 0 | AC9: 0 | AD9: S/S | AE9: ELUCERO | AG9: 0 | AH9: 0.35486111 | AI9: 46148
A10: 995674 | B10: 46144 | C10: SOSA, SILVIA | D10: 51 | E10: F | F10: OSPIA | G10: 27240990364 | I10: Lista para Facturar | J10: Exento | K10: CMSR CD RX-TAC 61037/0 | L10: 1 | N10: MAMOGRAFIA | O10: DIAGNOSR | P10: DIAGNOSR - CENTRO DEL DIAGNOSTICO | Q10: NO | R10: NNM | S10: 340602 | T10: MAMOGRAFIA CON PROY.AXILAR | U10: SIN REGION | V10: 2 | W10: ZUÑIGA, IRMA | X10: 0 | Y10: PLA, CAMILA | Z10: 10 | AA10: 0 | AB10: 0 | AC10: 10 | AD10: S/S | AE10: ELUCERO | AG10: 20 | AH10: 0.35625 | AI10: 46148
A11: 995674 | B11: 46144 | C11: SOSA, SILVIA | D11: 51 | E11: F | F11: OSPIA | G11: 27240990364 | I11: Lista para Facturar | J11: Exento | K11: CMSR CD RX-TAC 61037/0 | L11: 1 | N11: MAMOGRAFIA | O11: DIAGNOSR | P11: DIAGNOSR - CENTRO DEL DIAGNOSTICO | Q11: NO | R11: NNM | S11: 340601 | T11: MAMOGRAFIA (SENOGRAFIA) | U11: SIN REGION | V11: 2 | W11: ZUÑIGA, IRMA | X11: 0 | Y11: PLA, CAMILA | Z11: 10 | AA11: 0 | AB11: 0 | AC11: 10 | AD11: S/S | AE11: ELUCERO | AG11: 20 | AH11: 0.35625 | AI11: 46148
A12: 995675 | B12: 46144 | C12: IZUEL, MARIA TERESA | D12: 71 | E12: M | F12: PAMI AMB CC | G12: 150653937803/00 | I12: Lista para Facturar | J12: Exento | K12: IMAGEN SALUD | L12: 2 | N12: DENSITOMETRIA | O12: DIAGNOSR | P12: DIAGNOSR - CENTRO DEL DIAGNOSTICO | Q12: NO | R12: NNM | S12: 341202 | T12: DENSITOMETRIA OSEA DOS O MAS R | U12: SIN REGION | V12: 1 | W12: SANZ, CARLOS | X12: 0 | Y12: OBLITAS, ROCIO | Z12: 0 | AA12: 0 | AB12: 0 | AC12: 0 | AD12: S/S | AE12: ESLUCERO | AG12: 0 | AH12: 0.35625 | AI12: 46148
A13: 995676 | B13: 46144 | C13: FERNANDEZ, ELENA | D13: 80 | E13: F | F13: PAMI AMB CC | G13: 150290982704/00 | I13: Lista para Facturar | J13: Exento | K13: UNICO | L13: 1 | N13: RADIOLOGIA | O13: DIAGNOSR | P13: DIAGNOSR - CENTRO DEL DIAGNOSTICO | Q13: NO | R13: NNM | S13: 340213 | T13: RX CODO MANO PIE 2 X/PLACA 1EX | U13: SIN REGION | V13: 2 | W13: SOSA AVILA, DIEGO | X13: 0 | Y13: VARELA, JULIO | Z13: 0 | AA13: 0 | AB13: 0 | AC13: 0 | AD13: S/S | AE13: ELUCERO | AG13: 0 | AH13: 0.35833333 | AI13: 46148
A14: 995677 | B14: 46144 | C14: ARGUELLO, ELBA NELIDA | D14: 67 | E14: F | F14: PAMI AMB CC | G14: 140922868908/00 | I14: Lista para Facturar | J14: Exento | K14: IMAGEN SALUD | L14: 2 | N14: DENSITOMETRIA | O14: DIAGNOSR | P14: DIAGNOSR - CENTRO DEL DIAGNOSTICO | Q14: NO | R14: NNM | S14: 341202 | T14: DENSITOMETRIA OSEA DOS O MAS R | U14: SIN REGION | V14: 1 | W14: ROLDAN, BRIAN | X14: 0 | Y14: OBLITAS, ROCIO | Z14: 0 | AA14: 0 | AB14: 0 | AC14: 0 | AD14: S/S | AE14: ESLUCERO | AG14: 0 | AH14: 0.35833333 | AI14: 46148
A15: 995678 | B15: 46144 | C15: PONS, MERCEDES DEL VALLE | D15: 76 | E15: F | F15: PAMI AMB CC | G15: 150578942600/00 | I15: Lista para Facturar | J15: Exento | K15: IMAGEN SALUD | L15: 2 | N15: DENSITOMETRIA | O15: DIAGNOSR | P15: DIAGNOSR - CENTRO DEL DIAGNOSTICO | Q15: NO | R15: NNM | S15: 341202 | T15: DENSITOMETRIA OSEA DOS O MAS R | U15: SIN REGION | V15: 1 | W15: CUELLO, ISIDRO | X15: 0 | Y15: OBLITAS, ROCIO | Z15: 0 | AA15: 0 | AB15: 0 | AC15: 0 | AD15: S/S | AE15: ELUCERO | AG15: 0 | AH15: 0.36041667 | AI15: 46148
A16: 995679 | B16: 46144 | C16: MANSILLA, GREGORIA | D16: 81 | E16: F | F16: PAMI AMB CC | G16: 150145891701/00 | I16: Lista para Facturar | J16: Exento | K16: IMAGEN SALUD | L16: 2 | N16: DENSITOMETRIA | O16: DIAGNOSR | P16: DIAGNOSR - CENTRO DEL DIAGNOSTICO | Q16: NO | R16: NNM | S16: 341201 | T16: DENSITOMETRIA OSEA | U16: SIN REGION | V16: 1 | W16: SEPUR, PEDRO MARTIN | X16: 0 | Y16: OBLITAS, ROCIO | Z16: 0 | AA16: 0 | AB16: 0 | AC16: 0 | AD16: S/S | AE16: ESLUCERO | AG16: 0 | AH16: 0.35972222 | AI16: 46148
A17: 995680 | B17: 46144 | C17: DIAZ, ELBA | D17: 69 | E17: F | F17: PAMI AMB CC | G17: 150078890803/00 | I17: Lista para Facturar | J17: Exento | K17: UNICO | L17: 1 | N17: RADIOLOGIA | O17: DIAGNOSR | P17: DIAGNOSR - CENTRO DEL DIAGNOSTICO | Q17: NO | R17: NNM | S17: 340916 | T17: RADIOGRAFIA PANORAMICA DE CADE | U17: SIN REGION | V17: 1 | W17: ZOTELO, YANINA | X17: 0 | Y17: VARELA, JULIO | Z17: 0 | AA17: 0 | AB17: 0 | AC17: 0 | AD17: S/S | AE17: ELUCERO | AG17: 0 | AH17: 0.3625 | AI17: 46148
A18: 995681 | B18: 46144 | C18: CORIA, ROSA CARMEN | D18: 72 | E18: M | F18: PAMI AMB CC | G18: 150636291101/00 | I18: Lista para Facturar | J18: Exento | K18: IMAGEN SALUD | L18: 2 | N18: DENSITOMETRIA | O18: DIAGNOSR | P18: DIAGNOSR - CENTRO DEL DIAGNOSTICO | Q18: NO | R18: NNM | S18: 341202 | T18: DENSITOMETRIA OSEA DOS O MAS R | U18: SIN REGION | V18: 1 | W18: VEIGA, SABRINA | X18: 0 | Y18: OBLITAS, ROCIO | Z18: 0 | AA18: 0 | AB18: 0 | AC18: 0 | AD18: S/S | AE18: ESLUCERO | AG18: 0 | AH18: 0.36319444 | AI18: 46148
A19: 995682 | B19: 46144 | C19: RIBOTTA, RAUL | D19: 81 | E19: M | F19: PAMI AMB CC | G19: 150501234707/00 | I19: Lista para Facturar | J19: Exento | K19: UNICO | L19: 1 | N19: RADIOLOGIA | O19: DIAGNOSR | P19: DIAGNOSR - CENTRO DEL DIAGNOSTICO | Q19: NO | R19: NNM | S19: 340213 | T19: RX CODO MANO PIE 2 X/PLACA 1EX | U19: SIN REGION | V19: 4 | W19: CARLEVARIS, LEANDRO | X19: 0 | Y19: VARELA, JULIO | Z19: 0 | AA19: 0 | AB19: 0 | AC19: 0 | AD19: S/S | AE19: ESLUCERO | AG19: 0 | AH19: 0.37083333 | AI19: 46148
A20: 995682 | B20: 46144 | C20: RIBOTTA, RAUL | D20: 81 | E20: M | F20: PAMI AMB CC | G20: 150501234707/00 | I20: Lista para Facturar | J20: Exento | K20: UNICO | L20: 1 | N20: RADIOLOGIA | O20: DIAGNOSR | P20: DIAGNOSR - CENTRO DEL DIAGNOSTICO | Q20: NO | R20: NNM | S20: 340209 | T20: RX RAQUIS-COLUMNA- 1 EXP. | U20: SIN REGION | V20: 1 | W20: CARLEVARIS, LEANDRO | X20: 0 | Y20: VARELA, JULIO | Z20: 0 | AA20: 0 | AB20: 0 | AC20: 0 | AD20: S/S | AE20: ESLUCERO | AG20: 0 | AH20: 0.37083333 | AI20: 46148
A21: 995682 | B21: 46144 | C21: RIBOTTA, RAUL | D21: 81 | E21: M | F21: PAMI AMB CC | G21: 150501234707/00 | I21: Lista para Facturar | J21: Exento | K21: UNICO | L21: 1 | N21: RADIOLOGIA | O21: DIAGNOSR | P21: DIAGNOSR - CENTRO DEL DIAGNOSTICO | Q21: NO | R21: NNM | S21: 340210 | T21: RX RAQUIS-COLUMNA-EXP. SUBS. | U21: SIN REGION | V21: 1 | W21: CARLEVARIS, LEANDRO | X21: 0 | Y21: VARELA, JULIO | Z21: 0 | AA21: 0 | AB21: 0 | AC21: 0 | AD21: S/S | AE21: ESLUCERO | AG21: 0 | AH21: 0.37083333 | AI21: 46148
A22: 995682 | B22: 46144 | C22: RIBOTTA, RAUL | D22: 81 | E22: M | F22: PAMI AMB CC | G22: 150501234707/00 | I22: Lista para Facturar | J22: Exento | K22: UNICO | L22: 1 | N22: RADIOLOGIA | O22: DIAGNOSR | P22: DIAGNOSR - CENTRO DEL DIAGNOSTICO | Q22: NO | R22: NNM | S22: 340211 | T22: RX HOMBRO HUMERO PELVIS CADERA | U22: SIN REGION | V22: 1 | W22: CARLEVARIS, LEANDRO | X22: 0 | Y22: VARELA, JULIO | Z22: 0 | AA22: 0 | AB22: 0 | AC22: 0 | AD22: S/S | AE22: ESLUCERO | AG22: 0 | AH22: 0.37083333 | AI22: 46148
A23: 995683 | B23: 46144 | C23: ZELADA, FELIPA | D23: 81 | E23: F | F23: PAMI AMB CC | G23: 150292767108/00 | I23: Lista para Facturar | J23: Exento | K23: UNICO | L23: 1 | N23: TOMOGRAFIA | O23: DIAGNOSR | P23: DIAGNOSR - CENTRO DEL DIAGNOSTICO | Q23: NO | R23: NNM | S23: 341018 | T23: TOMOGRAFIA AXIAL COMPUTADA DE | U23: ABDOMEN | V23: 1 | W23: GERARDI, FRANCISCO JAVIER | X23: 0 | Y23: ASIGNADO, POR RIS | Z23: 0 | AA23: 0 | AB23: 0 | AC23: 0 | AD23: S/S | AE23: ELUCERO | AG23: 0 | AH23: 0.38125 | AI23: 46148
... A27: 995686 | B27: 46144 | C27: DIAZ, EVA ESTELA | D27: 74 | E27: F | F27: PAMI AMB CC | G27: 150634893205/00 | I27: Lista para Facturar | J27: Exento | K27: UNICO | L27: 1 | N27: RADIOLOGIA | O27: DIAGNOSR | P27: MALARG - MALARGUE | Q27: NO | R27: NNM | S27: 340302 | T27: RX TORAX EXP. SUBS. | U27: SIN REGION | V27: 1 | W27: SEPUR, PEDRO MARTIN | X27: 0 | Y27: VARELA, JULIO | Z27: 0 | AA27: 0 | AB27: 0 | AC27: 0 | AD27: S/S | AE27: LOJEDA | AG27: 0 | AH27: 0.38611111 | AI27: 46148
A28: 995687 | B28: 46144 | C28: BARDARO, NICOLAS | D28: 13 | E28: M | F28: MEDIFE | G28: 30665069803000 | I28: Lista para Facturar | J28: Exento | K28: CMSR CD RX-TAC 61037/0 | L28: 1 | N28: RADIOLOGIA | O28: DIAGNOSR | P28: DIAGNOSR - CENTRO DEL DIAGNOSTICO | Q28: NO | R28: NNM | S28: 340301 | T28: RX DE TORAX | U28: SIN REGION | V28: 1 | W28: TROYANO, RICARDO | X28: 0 | Y28: VARELA, JULIO | Z28: 0 | AA28: 0 | AB28: 0 | AC28: 0 | AD28: S/S | AE28: ESLUCERO | AG28: 0 | AH28: 0.38402778 | AI28: 46148
A29: 995687 | B29: 46144 | C29: BARDARO, NICOLAS | D29: 13 | E29: M | F29: MEDIFE | G29: 30665069803000 | I29: Lista para Facturar | J29: Exento | K29: CMSR CD RX-TAC 61037/0 | L29: 1 | N29: RADIOLOGIA | O29: DIAGNOSR | P29: DIAGNOSR - CENTRO DEL DIAGNOSTICO | Q29: NO | R29: NNM | S29: 340302 | T29: RX TORAX EXP. SUBS. | U29: SIN REGION | V29: 1 | W29: TROYANO, RICARDO | X29: 0 | Y29: VARELA, JULIO | Z29: 0 | AA29: 0 | AB29: 0 | AC29: 0 | AD29: S/S | AE29: ESLUCERO | AG29: 0 | AH29: 0.38402778 | AI29: 46148
A30: 995688 | B30: 46144 | C30: CATALAN, APOLINARIO | D30: 78 | E30: M | F30: PAMI AMB CC | G30: 150580886607/00 | I30: Lista para Facturar | J30: Exento | K30: UNICO | L30: 1 | N30: RADIOLOGIA | O30: DIAGNOSR | P30: MALARG - MALARGUE | Q30: NO | R30: NNM | S30: 340211 | T30: RX HOMBRO HUMERO PELVIS CADERA | U30: SIN REGION | V30: 1 | W30: SEPUR, PEDRO MARTIN | X30: 0 | Y30: VARELA, JULIO | Z30: 0 | AA30: 0 | AB30: 0 | AC30: 0 | AD30: S/S | AE30: LOJEDA | AG30: 0 | AH30: 0.3875 | AI30: 46148
A31: 995689 | B31: 46144 | C31: RUIZ, CLAUDIA CRISTINA | D31: 59 | E31: F | F31: PAMI AMB CC | G31: 150927518608/01 | I31: Lista para Facturar | J31: Exento | K31: UNICO | L31: 1 | N31: RADIOLOGIA | O31: DIAGNOSR | P31: DIAGNOSR - CENTRO DEL DIAGNOSTICO | Q31: NO | R31: NNM | S31: 340213 | T31: RX CODO MANO PIE 2 X/PLACA 1EX | U31: SIN REGION | V31: 2 | W31: GERARDI, FRANCISCO JAVIER | X31: 0 | Y31: VARELA, JULIO | Z31: 0 | AA31: 0 | AB31: 0 | AC31: 0 | AD31: S/S | AE31: ELUCERO | AG31: 0 | AH31: 0.38819444 | AI31: 46148
A32: 995690 | B32: 46144 | C32: BENEDETTO, CARLOS ALBERTO | D32: 74 | E32: M | F32: PAMI AMB CC | G32: 150631767202/00 | I32: Lista para Facturar | J32: Exento | K32: UNICO | L32: 1 | N32: RADIOLOGIA | O32: DIAGNOSR | P32: MALARG - MALARGUE | Q32: NO | R32: NNM | S32: 340209 | T32: RX RAQUIS-COLUMNA- 1 EXP. | U32: SIN REGION | V32: 1 | W32: SEPUR, PEDRO MARTIN | X32: 0 | Y32: VARELA, JULIO | Z32: 0 | AA32: 0 | AB32: 0 | AC32: 0 | AD32: S/S | AE32: LOJEDA | AG32: 0 | AH32: 0.38819444 | AI32: 46148
A33: 995690 | B33: 46144 | C33: BENEDETTO, CARLOS ALBERTO | D33: 74 | E33: M | F33: PAMI AMB CC | G33: 150631767202/00 | I33: Lista para Facturar | J33: Exento | K33: UNICO | L33: 1 | N33: RADIOLOGIA | O33: DIAGNOSR | P33: MALARG - MALARGUE | Q33: NO | R33: NNM | S33: 340210 | T33: RX RAQUIS-COLUMNA-EXP. SUBS. | U33: SIN REGION | V33: 1 | W33: SEPUR, PEDRO MARTIN | X33: 0 | Y33: VARELA, JULIO | Z33: 0 | AA33: 0 | AB33: 0 | AC33: 0 | AD33: S/S | AE33: LOJEDA | AG33: 0 | AH33: 0.38819444 | AI33: 46148
A34: 995691 | B34: 46144 | C34: CARA, MARIA HORTENCIA | D34: 51 | E34: F | F34: H REGIONAL MG | G34: 24169379 | I34: Lista para Facturar | J34: Exento | K34: UNICO | L34: 1 | N34: TOMOGRAFIA | O34: DIAGNOSR | P34: MALARG - MALARGUE | Q34: NO | R34: NNM | S34: 922026 | T34: TOMOGRAFIA COMPUTADA MULTICORT | U34: SIN REGION | V34: 1 | W34: GIORDANINI, SERGIO | X34: 0 | Y34: ASIGNADO, POR RIS | Z34: 0 | AA34: 0 | AB34: 0 | AC34: 0 | AD34: S/S | AE34: CIRIARTE | AG34: 0 | AH34: 0.38819444 | AI34: 46148
A35: 995692 | B35: 46144 | C35: HEREDIA, MARIA LEONOR | D35: 73 | E35: M | F35: PAMI AMB CC | G35: 115341247848/00 | I35: Lista para Facturar | J35: Exento | K35: UNICO | L35: 1 | N35: TOMOGRAFIA | O35: DIAGNOSR | P35: DIAGNOSR - CENTRO DEL DIAGNOSTICO | Q35: NO | R35: NNM | S35: 341008 | T35: TOMOGRAFIA COMPUTADA ABDOMINAL | U35: ABD. Y PELVIS | V35: 1 | W35: PEREZ, JOSE LUIS | X35: 0 | Y35: ASIGNADO, POR RIS | Z35: 0 | AA35: 0 | AB35: 0 | AC35: 0 | AD35: S/S | AE35: ESLUCERO | AG35: 0 | AH35: 0.38888889 | AI35: 46148
A36: 995693 | B36: 46144 | C36: PERE, HAYDEE | D36: 66 | E36: F | F36: PAMI AMB CC | G36: 155075039707/00 | I36: Lista para Facturar | J36: Exento | K36: IMAGEN SALUD | L36: 2 | N36: DENSITOMETRIA | O36: DIAGNOSR | P36: DIAGNOSR - CENTRO DEL DIAGNOSTICO | Q36: NO | R36: NNM | S36: 341202 | T36: DENSITOMETRIA OSEA DOS O MAS R | U36: SIN REGION | V36: 1 | W36: CARLEVARIS, LEANDRO | X36: 0 | Y36: OBLITAS, ROCIO | Z36: 0 | AA36: 0 | AB36: 0 | AC36: 0 | AD36: S/S | AE36: ELUCERO | AG36: 0 | AH36: 0.39166667 | AI36: 46148
A37: 995694 | B37: 46144 | C37: CAIAZZA REIA, ANIELLO | D37: 75 | E37: M | F37: PAMI AMB CC | G37: 150992887508/00 | I37: Lista para Facturar | J37: Exento | K37: UNICO | L37: 1 | N37: RADIOLOGIA | O37: DIAGNOSR | P37: DIAGNOSR - CENTRO DEL DIAGNOSTICO | Q37: NO | R37: NNM | S37: 340214 | T37: MED. COMPARATIVA DE M.I.XESTUD | U37: SIN REGION | V37: 1 | W37: LUFFI, MARIA YAMILA | X37: 0 | Y37: VARELA, JULIO | Z37: 0 | AA37: 0 | AB37: 0 | AC37: 0 | AD37: S/S | AE37: ELUCERO | AG37: 0 | AH37: 0.39375 | AI37: 46148
A38: 995695 | B38: 46144 | C38: MADARIETA, CARMEN RAQUEL | D38: 78 | E38: F | F38: PAMI AMB CC | G38: 150391498709/00 | I38: Lista para Facturar | J38: Exento | K38: IMAGEN SALUD | L38: 2 | N38: DENSITOMETRIA | O38: DIAGNOSR | P38: DIAGNOSR - CENTRO DEL DIAGNOSTICO | Q38: NO | R38: NNM | S38: 341202 | T38: DENSITOMETRIA OSEA DOS O MAS R | U38: SIN REGION | V38: 1 | W38: OBLITAS, ROCIO | X38: 0 | Y38: OBLITAS, ROCIO | Z38: 0 | AA38: 0 | AB38: 0 | AC38: 0 | AD38: S/S | AE38: ELUCERO | AG38: 0 | AH38: 0.39583333 | AI38: 46148
A39: 995696 | B39: 46144 | C39: VILLAR, IRMA NELIDA | D39: 72 | E39: F | F39: PAMI AMB CC | G39: 150634924604/00 | I39: Lista para Facturar | J39: Exento | K39: UNICO | L39: 1 | N39: RADIOLOGIA | O39: DIAGNOSR | P39: MALARG - MALARGUE | Q39: NO | R39: NNM | S39: 340209 | T39: RX RAQUIS-COLUMNA- 1 EXP. | U39: SIN REGION | V39: 1 | W39: SEPUR, PEDRO MARTIN | X39: 0 | Y39: VARELA, JULIO | Z39: 0 | AA39: 0 | AB39: 0 | AC39: 0 | AD39: S/S | AE39: LOJEDA | AG39: 0 | AH39: 0.39583333 | AI39: 46148
A40: 995696 | B40: 46144 | C40: VILLAR, IRMA NELIDA | D40: 72 | E40: F | F40: PAMI AMB CC | G40: 150634924604/00 | I40: Lista para Facturar | J40: Exento | K40: UNICO | L40: 1 | N40: RADIOLOGIA | O40: DIAGNOSR | P40: MALARG - MALARGUE | Q40: NO | R40: NNM | S40: 340210 | T40: RX RAQUIS-COLUMNA-EXP. SUBS. | U40: SIN REGION | V40: 1 | W40: SEPUR, PEDRO MARTIN | X40: 0 | Y40: VARELA, JULIO | Z40: 0 | AA40: 0 | AB40: 0 | AC40: 0 | AD40: S/S | AE40: LOJEDA | AG40: 0 | AH40: 0.39583333 | AI40: 46148
A41: 995696 | B41: 46144 | C41: VILLAR, IRMA NELIDA | D41: 72 | E41: F | F41: PAMI AMB CC | G41: 150634924604/00 | I41: Lista para Facturar | J41: Exento | K41: UNICO | L41: 1 | N41: RADIOLOGIA | O41: DIAGNOSR | P41: MALARG - MALARGUE | Q41: NO | R41: NNM | S41: 340211 | T41: RX HOMBRO HUMERO PELVIS CADERA | U41: SIN REGION | V41: 2 | W41: SEPUR, PEDRO MARTIN | X41: 0 | Y41: VARELA, JULIO | Z41: 0 | AA41: 0 | AB41: 0 | AC41: 0 | AD41: S/S | AE41: LOJEDA | AG41: 0 | AH41: 0.39583333 | AI41: 46148
A42: 995696 | B42: 46144 | C42: VILLAR, IRMA NELIDA | D42: 72 | E42: F | F42: PAMI AMB CC | G42: 150634924604/00 | I42: Lista para Facturar | J42: Exento | K42: UNICO | L42: 1 | N42: RADIOLOGIA | O42: DIAGNOSR | P42: MALARG - MALARGUE | Q42: NO | R42: NNM | S42: 340212 | T42: POR EXPOSICION SUBSIGUIENTE | U42: SIN REGION | V42: 1 | W42: SEPUR, PEDRO MARTIN | X42: 0 | Y42: VARELA, JULIO | Z42: 0 | AA42: 0 | AB42: 0 | AC42: 0 | AD42: S/S | AE42: LOJEDA | AG42: 0 | AH42: 0.39583333 | AI42: 46148
A43: 995696 | B43: 46144 | C43: VILLAR, IRMA NELIDA | D43: 72 | E43: F | F43: PAMI AMB CC | G43: 150634924604/00 | I43: Lista para Facturar | J43: Exento | K43: UNICO | L43: 1 | N43: RADIOLOGIA | O43: DIAGNOSR | P43: MALARG - MALARGUE | Q43: NO | R43: NNM | S43: 340213 | T43: RX CODO MANO PIE 2 X/PLACA 1EX | U43: SIN REGION | V43: 2 | W43: SEPUR, PEDRO MARTIN | X43: 0 | Y43: VARELA, JULIO | Z43: 0 | AA43: 0 | AB43: 0 | AC43: 0 | AD43: S/S | AE43: LOJEDA | AG43: 0 | AH43: 0.39583333 | AI43: 46148
A44: 995697 | B44: 46144 | C44: APPIOLAZA, NANCY MABEL | D44: 69 | E44: F | F44: PAMI AMB CC | G44: 155503278405/00 | I44: Lista para Facturar | J44: Exento | K44: UNICO | L44: 1 | N44: RADIOLOGIA | O44: DIAGNOSR | P44: MALARG - MALARGUE | Q44: NO | R44: NNM | S44: 340213 | T44: RX CODO MANO PIE 2 X/PLACA 1EX | U44: SIN REGION | V44: 2 | W44: SEPUR, PEDRO MARTIN | X44: 0 | Y44: VARELA, JULIO | Z44: 0 | AA44: 0 | AB44: 0 | AC44: 0 | AD44: S/S | AE44: LOJEDA | AG44: 0 | AH44: 0.39791667 | AI44: 46148
A45: 995697 | B45: 46144 | C45: APPIOLAZA, NANCY MABEL | D45: 69 | E45: F | F45: PAMI AMB CC | G45: 155503278405/00 | I45: Lista para Facturar | J45: Exento | K45: UNICO | L45: 1 | N45: RADIOLOGIA | O45: DIAGNOSR | P45: MALARG - MALARGUE | Q45: NO | R45: NNM | S45: 340211 | T45: RX HOMBRO HUMERO PELVIS CADERA | U45: SIN REGION | V45: 1 | W45: SEPUR, PEDRO MARTIN | X45: 0 | Y45: VARELA, JULIO | Z45: 0 | AA45: 0 | AB45: 0 | AC45: 0 | AD45: S/S | AE45: LOJEDA | AG45: 0 | AH45: 0.39791667 | AI45: 46148
A46: 995697 | B46: 46144 | C46: APPIOLAZA, NANCY MABEL | D46: 69 | E46: F | F46: PAMI AMB CC | G46: 155503278405/00 | I46: Lista para Facturar | J46: Exento | K46: UNICO | L46: 1 | N46: RADIOLOGIA | O46: DIAGNOSR | P46: MALARG - MALARGUE | Q46: NO | R46: NNM | S46: 340212 | T46: POR EXPOSICION SUBSIGUIENTE | U46: SIN REGION | V46: 1 | W46: SEPUR, PEDRO MARTIN | X46: 0 | Y46: VARELA, JULIO | Z46: 0 | AA46: 0 | AB46: 0 | AC46: 0 | AD46: S/S | AE46: LOJEDA | AG46: 0 | AH46: 0.39791667 | AI46: 46148
A47: 995698 | B47: 46144 | C47: CASADO, ANALIA | D47: 69 | E47: F | F47: PAMI AMB CC | G47: 150071265801/00 | I47: Pendiente | J47: Exento | K47: UNICO | L47: 1 | N47: RADIOLOGIA | O47: DIAGNOSR | P47: DIAGNOSR - CENTRO DEL DIAGNOSTICO | Q47: NO | R47: NNM | S47: 340213 | T47: RX CODO MANO PIE 2 X/PLACA 1EX | U47: SIN REGION | V47: 4 | W47: GALLI, SONIA | X47: 0 | Y47: VARELA, JULIO | Z47: 0 | AA47: 0 | AB47: 0 | AC47: 0 | AD47: S/S | AE47: ELUCERO | AF47: Trat.Prolongado: Consumos incompletos | AG47: 0 | AH47: 0.39861111 | AI47: 46148
A48: 995699 | B48: 46144 | C48: NAVARRO, MARGOT | D48: 67 | E48: F | F48: PAMI AMB CC | G48: 140921799207/00 | I48: Lista para Facturar | J48: Exento | K48: UNICO | L48: 1 | N48: RADIOLOGIA | O48: DIAGNOSR | P48: DIAGNOSR - CENTRO DEL DIAGNOSTICO | Q48: NO | R48: NNM | S48: 340202 | T48: RX CRANEO CARA SENOS PAR.SUBS | U48: SIN REGION | V48: 1 | W48: MONTOYA, PAOLA | X48: 0 | Y48: VARELA, JULIO | Z48: 0 | AA48: 0 | AB48: 0 | AC48: 0 | AD48: S/S | AE48: ELUCERO | AG48: 0 | AH48: 0.40138889 | AI48: 46148
A49: 995699 | B49: 46144 | C49: NAVARRO, MARGOT | D49: 67 | E49: F | F49: PAMI AMB CC | G49: 140921799207/00 | I49: Lista para Facturar | J49: Exento | K49: UNICO | L49: 1 | N49: RADIOLOGIA | O49: DIAGNOSR | P49: DIAGNOSR - CENTRO DEL DIAGNOSTICO | Q49: NO | R49: NNM | S49: 340201 | T49: RX CRANEO CARA SENOS PAR. 1EXP | U49: SIN REGION | V49: 1 | W49: MONTOYA, PAOLA | X49: 0 | Y49: VARELA, JULIO | Z49: 0 | AA49: 0 | AB49: 0 | AC49: 0 | AD49: S/S | AE49: ELUCERO | AG49: 0 | AH49: 0.40138889 | AI49: 46148
A50: 995700 | B50: 46144 | C50: DIAZ, ROBERTO | D50: 73 | E50: M | F50: PAMI AMB CC | G50: 140907738303/00 | I50: Lista para Facturar | J50: Exento | K50: IMAGEN SALUD | L50: 2 | N50: DENSITOMETRIA | O50: DIAGNOSR | P50: DIAGNOSR - CENTRO DEL DIAGNOSTICO | Q50: NO | R50: NNM | S50: 341202 | T50: DENSITOMETRIA OSEA DOS O MAS R | U50: SIN REGION | V50: 1 | W50: OBLITAS, ROCIO | X50: 0 | Y50: OBLITAS, ROCIO | Z50: 0 | AA50: 0 | AB50: 0 | AC50: 0 | AD50: S/S | AE50: ESLUCERO | AG50: 0 | AH50: 0.40138889 | AI50: 46148
A51: 995701 | B51: 46144 | C51: DIAZ, ROBERTO | D51: 73 | E51: M | F51: PAMI AMB CC | G51: 140907738303/00 | I51: Lista para Facturar | J51: Exento | K51: UNICO | L51: 1 | N51: RADIOLOGIA | O51: DIAGNOSR | P51: DIAGNOSR - CENTRO DEL DIAGNOSTICO | Q51: NO | R51: NNM | S51: 340222 | T51: ESPINOGRAMA | U51: SIN REGION | V51: 1 | W51: OBLITAS, ROCIO | X51: 0 | Y51: ASIGNADO, POR RIS | Z51: 0 | AA51: 0 | AB51: 0 | AC51: 0 | AD51: S/S | AE51: ESLUCERO | AG51: 0 | AH51: 0.40277778 | AI51: 46148
A52: 995702 | B52: 46144 | C52: RUIZ, ANTONIA | D52: 65 | E52: F | F52: PAMI AMB CC | G52: 140907738303/01 | I52: Lista para Facturar | J52: Exento | K52: UNICO | L52: 1 | N52: RADIOLOGIA | O52: DIAGNOSR | P52: DIAGNOSR - CENTRO DEL DIAGNOSTICO | Q52: NO | R52: NNM | S52: 340209 | T52: RX RAQUIS-COLUMNA- 1 EXP. | U52: SIN REGION | V52: 1 | W52: ABAURRE, DAVID | X52: 0 | Y52: VARELA, JULIO | Z52: 0 | AA52: 0 | AB52: 0 | AC52: 0 | AD52: S/S | AE52: ESLUCERO | AG52: 0 | AH52: 0.40486111 | AI52: 46148
A53: 995702 | B53: 46144 | C53: RUIZ, ANTONIA | D53: 65 | E53: F | F53: PAMI AMB CC | G53: 140907738303/01 | I53: Lista para Facturar | J53: Exento | K53: UNICO | L53: 1 | N53: RADIOLOGIA | O53: DIAGNOSR | P53: DIAGNOSR - CENTRO DEL DIAGNOSTICO | Q53: NO | R53: NNM | S53: 340210 | T53: RX RAQUIS-COLUMNA-EXP. SUBS. | U53: SIN REGION | V53: 1 | W53: ABAURRE, DAVID | X53: 0 | Y53: VARELA, JULIO | Z53: 0 | AA53: 0 | AB53: 0 | AC53: 0 | AD53: S/S | AE53: ESLUCERO | AG53: 0 | AH53: 0.40486111 | AI53: 46148
A54: 995703 | B54: 46144 | C54: GALDAMEZ, RAMON LAUREANO | D54: 61 | E54: M | F54: H REGIONAL MG | G54: 16954591 | I54: Lista para Facturar | J54: Exento | K54: UNICO | L54: 1 | N54: TOMOGRAFIA | O54: DIAGNOSR | P54: MALARG - MALARGUE | Q54: NO | R54: NNM | S54: 922026 | T54: TOMOGRAFIA COMPUTADA MULTICORT | U54: SIN REGION | V54: 1 | W54: SOLER, BERNARDITA | X54: 0 | Y54: ASIGNADO, POR RIS | Z54: 0 | AA54: 0 | AB54: 0 | AC54: 0 | AD54: S/S | AE54: CIRIARTE | AG54: 0 | AH54: 0.40972222 | AI54: 46148
A55: 995704 | B55: 46144 | C55: MODON, MIRTA | D55: 71 | E55: F | F55: PAMI AMB CC | G55: 150649829904/00 | I55: Lista para Facturar | J55: Exento | K55: UNICO | L55: 1 | N55: TOMOGRAFIA | O55: DIAGNOSR | P55: DIAGNOSR - CENTRO DEL DIAGNOSTICO | Q55: NO | R55: NNM | S55: 341010 | T55: TOMOGRAFIA COMPUTADA TORACICA | U55: SIN REGION | V55: 1 | W55: MARTOS, PABLO | X55: 0 | Y55: ASIGNADO, POR RIS | Z55: 0 | AA55: 0 | AB55: 0 | AC55: 0 | AD55: S/S | AE55: ELUCERO | AG55: 0 | AH55: 0.41111111 | AI55: 46148
A56: 995705 | B56: 46144 | C56: DIAZ, CECILIA | D56: 35 | E56: F | F56: PARTICULAR CD | I56: Lista para Facturar | J56: Exento | K56: UNICO | L56: 1 | N56: RADIOLOGIA | O56: DIAGNOSR | P56: DIAGNOSR - CENTRO DEL DIAGNOSTICO | Q56: NO | R56: NNM | S56: 340272 | T56: ESPINOGRAMA COMPLETO FRENTE Y | U56: SIN REGION | V56: 1 | W56: SCIARRABBA, EDGARDO | X56: 0 | Y56: ASIGNADO, POR RIS | Z56: 450 | AA56: 0 | AB56: 0 | AC56: 0 | AD56: S/S | AE56: ESLUCERO | AG56: 900 | AH56: 0.4125 | AI56: 46148
A57: 995705 | B57: 46144 | C57: DIAZ, CECILIA | D57: 35 | E57: F | F57: PARTICULAR CD | I57: Lista para Facturar | J57: Exento | K57: UNICO | L57: 1 | N57: RADIOLOGIA | O57: DIAGNOSR | P57: DIAGNOSR - CENTRO DEL DIAGNOSTICO | Q57: NO | R57: NNM | S57: 340260 | T57: MEDICION COMPARAT DE MIEMBROS | U57: SIN REGION | V57: 1 | W57: SCIARRABBA, EDGARDO | X57: 0 | Y57: ASIGNADO, POR RIS | Z57: 450 | AA57: 0 | AB57: 0 | AC57: 0 | AD57: S/S | AE57: ESLUCERO | AG57: 900 | AH57: 0.4125 | AI57: 46148
A58: 995706 | B58: 46144 | C58: DIAZ, NORMA | D58: 63 | E58: F | F58: PAMI AMB CC | G58: 155490843202/00 | I58: Anulada | J58: Exento | K58: UNICO | L58: 1 | N58: RADIOLOGIA | O58: DIAGNOSR | P58: DIAGNOSR - CENTRO DEL DIAGNOSTICO | Q58: NO | R58: NNM | S58: 340301 | T58: RX DE TORAX | U58: SIN REGION | V58: 1 | W58: CARLEVARIS, LEANDRO | X58: 0 | Y58: VARELA, JULIO | Z58: 0 | AA58: 0 | AB58: 0 | AC58: 0 | AD58: S/S | AE58: ELUCERO | AG58: 0 | AH58: 0.41458333 | AI58: 46148
A59: 995707 | B59: 46144 | C59: DIAZ, NORMA | D59: 63 | E59: F | F59: PAMI AMB CC | G59: 155490843202/00 | I59: Lista para Facturar | J59: Exento | K59: UNICO | L59: 1 | N59: RADIOLOGIA | O59: DIAGNOSR | P59: DIAGNOSR - CENTRO DEL DIAGNOSTICO | Q59: NO | R59: NNM | S59: 340301 | T59: RX DE TORAX | U59: SIN REGION | V59: 1 | W59: GERARDI, FRANCISCO JAVIER | X59: 0 | Y59: VARELA, JULIO | Z59: 0 | AA59: 0 | AB59: 0 | AC59: 0 | AD59: S/S | AE59: ESLUCERO | AG59: 0 | AH59: 0.41875 | AI59: 46148
A60: 995708 | B60: 46144 | C60: FUENZALIDA, IRENE CRISTINA | D60: 64 | E60: F | F60: PAMI AMB CC | G60: 155990528300/00 | I60: Lista para Facturar | J60: Exento | K60: UNICO | L60: 1 | N60: RADIOLOGIA | O60: DIAGNOSR | P60: MALARG - MALARGUE | Q60: NO | R60: NNM | S60: 340210 | T60: RX RAQUIS-COLUMNA-EXP. SUBS. | U60: SIN REGION | V60: 1 | W60: SEPUR, PEDRO MARTIN | X60: 0 | Y60: VARELA, JULIO | Z60: 0 | AA60: 0 | AB60: 0 | AC60: 0 | AD60: S/S | AE60: LOJEDA | AG60: 0 | AH60: 0.42222222 | AI60: 46148
A61: 995708 | B61: 46144 | C61: FUENZALIDA, IRENE CRISTINA | D61: 64 | E61: F | F61: PAMI AMB CC | G61: 155990528300/00 | I61: Lista para Facturar | J61: Exento | K61: UNICO | L61: 1 | N61: RADIOLOGIA | O61: DIAGNOSR | P61: MALARG - MALARGUE | Q61: NO | R61: NNM | S61: 340209 | T61: RX RAQUIS-COLUMNA- 1 EXP. | U61: SIN REGION | V61: 1 | W61: SEPUR, PEDRO MARTIN | X61: 0 | Y61: VARELA, JULIO | Z61: 0 | AA61: 0 | AB61: 0 | AC61: 0 | AD61: S/S | AE61: LOJEDA | AG61: 0 | AH61: 0.42222222 | AI61: 46148
A62: 995709 | B62: 46144 | C62: CASATTI, DEBORA | D62: 38 | E62: F | F62: SALUD LABORAL | G62: 32797987 | I62: Lista para Facturar | J62: Exento | K62: UNICO | L62: 1 | N62: RADIOLOGIA | O62: DIAGNOSR | P62: DIAGNOSR - CENTRO DEL DIAGNOSTICO | Q62: NO | R62: NNM | S62: 340209 | T62: RX RAQUIS-COLUMNA- 1 EXP. | U62: SIN REGION | V62: 2 | W62: A CONFIRMAR, . | X62: 0 | Y62: ASIGNADO, POR RIS | Z62: 0 | AA62: 0 | AB62: 0 | AC62: 0 | AD62: S/S | AE62: ESLUCERO | AG62: 0 | AH62: 0.42222222 | AI62: 46148
A63: 995709 | B63: 46144 | C63: CASATTI, DEBORA | D63: 38 | E63: F | F63: SALUD LABORAL | G63: 32797987 | I63: Lista para Facturar | J63: Exento | K63: UNICO | L63: 1 | N63: RADIOLOGIA | O63: DIAGNOSR | P63: DIAGNOSR - CENTRO DEL DIAGNOSTICO | Q63: NO | R63: NNM | S63: 340213 | T63: RX CODO MANO PIE 2 X/PLACA 1EX | U63: SIN REGION | V63: 2 | W63: A CONFIRMAR, . | X63: 0 | Y63: ASIGNADO, POR RIS | Z63: 0 | AA63: 0 | AB63: 0 | AC63: 0 | AD63: S/S | AE63: ESLUCERO | AG63: 0 | AH63: 0.42222222 | AI63: 46148
A64: 995709 | B64: 46144 | C64: CASATTI, DEBORA | D64: 38 | E64: F | F64: SALUD LABORAL | G64: 32797987 | I64: Lista para Facturar | J64: Exento | K64: UNICO | L64: 1 | N64: RADIOLOGIA | O64: DIAGNOSR | P64: DIAGNOSR - CENTRO DEL DIAGNOSTICO | Q64: NO | R64: NNM | S64: 340301 | T64: RX DE TORAX | U64: SIN REGION | V64: 1 | W64: A CONFIRMAR, . | X64: 0 | Y64: ASIGNADO, POR RIS | Z64: 0 | AA64: 0 | AB64: 0 | AC64: 0 | AD64: S/S | AE64: ESLUCERO | AG64: 0 | AH64: 0.42222222 | AI64: 46148
A65: 995709 | B65: 46144 | C65: CASATTI, DEBORA | D65: 38 | E65: F | F65: SALUD LABORAL | G65: 32797987 | I65: Lista para Facturar | J65: Exento | K65: UNICO | L65: 1 | N65: RADIOLOGIA | O65: DIAGNOSR | P65: DIAGNOSR - CENTRO DEL DIAGNOSTICO | Q65: NO | R65: NNM | S65: 340210 | T65: RX RAQUIS-COLUMNA-EXP. SUBS. | U65: SIN REGION | V65: 2 | W65: A CONFIRMAR, . | X65: 0 | Y65: ASIGNADO, POR RIS | Z65: 0 | AA65: 0 | AB65: 0 | AC65: 0 | AD65: S/S | AE65: ESLUCERO | AG65: 0 | AH65: 0.42222222 | AI65: 46148
A66: 995709 | B66: 46144 | C66: CASATTI, DEBORA | D66: 38 | E66: F | F66: SALUD LABORAL | G66: 32797987 | I66: Lista para Facturar | J66: Exento | K66: UNICO | L66: 1 | N66: RADIOLOGIA | O66: DIAGNOSR | P66: DIAGNOSR - CENTRO DEL DIAGNOSTICO | Q66: NO | R66: NNM | S66: 340209 | T66: RX RAQUIS-COLUMNA- 1 EXP. | U66: SIN REGION | V66: 4 | W66: A CONFIRMAR, . | X66: 0 | Y66: ASIGNADO, POR RIS | Z66: 0 | AA66: 0 | AB66: 0 | AC66: 0 | AD66: S/S | AE66: ESLUCERO | AG66: 0 | AH66: 0.42222222 | AI66: 46148
A67: 995710 | B67: 46144 | C67: CARNOVALE, ROSA | D67: 72 | E67: M | F67: PAMI AMB CC | G67: 150615552208/00 | I67: Lista para Facturar | J67: Exento | K67: UNICO | L67: 1 | N67: RADIOLOGIA | O67: DIAGNOSR | P67: MALARG - MALARGUE | Q67: NO | R67: NNM | S67: 340213 | T67: RX CODO MANO PIE 2 X/PLACA 1EX | U67: SIN REGION | V67: 2 | W67: CUELLO, ISIDRO | X67: 0 | Y67: VARELA, JULIO | Z67: 0 | AA67: 0 | AB67: 0 | AC67: 0 | AD67: S/S | AE67: LOJEDA | AG67: 0 | AH67: 0.42291667 | AI67: 46148
A68: 995711 | B68: 46144 | C68: SAEZ, GUSTAVO ARIEL | D68: 52 | E68: M | F68: OSEP MG | G68: 23711331/00 | I68: Lista para Facturar | J68: Exento | K68: UNICO | L68: 1 | N68: TOMOGRAFIA | O68: DIAGNOSR | P68: MALARG - MALARGUE | Q68: NO | R68: NNM | S68: 341012 | T68: TAC DE OTROS ORGANOS O REG.--- | U68: ANTEBRAZO | V68: 1 | W68: CASETTI, SILVIA | X68: 0 | Y68: ASIGNADO, POR RIS | Z68: 0 | AA68: 0 | AB68: 0 | AC68: 0 | AD68: S/S | AE68: CIRIARTE | AG68: 0 | AH68: 0.42638889 | AI68: 46148
A69: 995712 | B69: 46144 | C69: OJEDA, MARTA | D69: 72 | E69: F | F69: PAMI AMB CC | G69: 150597259204/00 | I69: Lista para Facturar | J69: Exento | K69: IMAGEN SALUD | L69: 2 | N69: DENSITOMETRIA | O69: DIAGNOSR | P69: DIAGNOSR - CENTRO DEL DIAGNOSTICO | Q69: NO | R69: NNM | S69: 341202 | T69: DENSITOMETRIA OSEA DOS O MAS R | U69: SIN REGION | V69: 1 | W69: OBLITAS, ROCIO | X69: 0 | Y69: OBLITAS, ROCIO | Z69: 0 | AA69: 0 | AB69: 0 | AC69: 0 | AD69: S/S | AE69: ESLUCERO | AG69: 0 | AH69: 0.42847222 | AI69: 46148
A70: 995713 | B70: 46144 | C70: CORREA, CLAUDIA ALEJANDRA | D70: 57 | E70: F | F70: OSEP MG | G70: 04478290/01 | I70: Lista para Facturar | J70: Exento | K70: UNICO | L70: 1 | N70: RADIOLOGIA | O70: DIAGNOSR | P70: MALARG - MALARGUE | Q70: NO | R70: NNM | S70: 340213 | T70: RX CODO MANO PIE 2 X/PLACA 1EX | U70: SIN REGION | V70: 1 | W70: FERNANDEZ, EZEQUIEL | X70: 0 | Y70: VARELA, JULIO | Z70: 0 | AA70: 0 | AB70: 0 | AC70: 0 | AD70: S/S | AE70: LOJEDA | AG70: 0 | AH70: 0.43194444 | AI70: 46148
A71: 995714 | B71: 46144 | C71: HERNANDEZ, OSCAR ENRIQUE | D71: 79 | E71: M | F71: PAMI INT CC | G71: 150539700106/00 | I71: Lista para Facturar | J71: Exento | K71: UNICO | L71: 1 | N71: TOMOGRAFIA | O71: DIAGNOSR | P71: DIAGNOSR - CENTRO DEL DIAGNOSTICO | Q71: NO | R71: NNM | S71: 341001 | T71: TOMOGRAFIA COMPUTADA CEREBRAL | U71: SIN REGION | V71: 1 | W71: RUBIO, DANIELA IVANA | X71: 0 | Y71: ASIGNADO, POR RIS | Z71: 0 | AA71: 0 | AB71: 0 | AC71: 0 | AD71: S/S | AE71: ESLUCERO | AG71: 0 | AH71: 0.43125 | AI71: 46148
A72: 995715 | B72: 46144 | C72: PEREZ, JUAN CARLOS | D72: 73 | E72: M | F72: PAMI AMB CC | G72: 140006156601/00 | I72: Lista para Facturar | J72: Exento | K72: UNICO | L72: 1 | N72: TOMOGRAFIA | O72: DIAGNOSR | P72: MALARG - MALARGUE | Q72: NO | R72: NNM | S72: 341019 | T72: TOMOGRAFIA AXIAL COMPUTADA TOR | U72: TORAX | V72: 1 | W72: YASUFF, YAIR | X72: 0 | Y72: ASIGNADO, POR RIS | Z72: 0 | AA72: 0 | AB72: 0 | AC72: 0 | AD72: S/S | AE72: CIRIARTE | AG72: 0 | AH72: 0.43333333 | AI72: 46148
A73: 995716 | B73: 46144 | C73: CARVALLO, HILDA GRACIELA | D73: 64 | E73: F | F73: PAMI AMB CC | G73: 140107277107/00 | I73: Lista para Facturar | J73: Exento | K73: IMAGEN SALUD | L73: 2 | N73: DENSITOMETRIA | O73: DIAGNOSR | P73: DIAGNOSR - CENTRO DEL DIAGNOSTICO | Q73: NO | R73: NNM | S73: 341202 | T73: DENSITOMETRIA OSEA DOS O MAS R | U73: SIN REGION | V73: 1 | W73: OBLITAS, ROCIO | X73: 0 | Y73: OBLITAS, ROCIO | Z73: 0 | AA73: 0 | AB73: 0 | AC73: 0 | AD73: S/S | AE73: ESLUCERO | AG73: 0 | AH73: 0.43958333 | AI73: 46148
A74: 995717 | B74: 46144 | C74: GONZALEZ, MARTA YOLANDA | D74: 86 | E74: F | F74: PAMI AMB CC | G74: 150156676201/00 | I74: Lista para Facturar | J74: Exento | K74: UNICO | L74: 1 | N74: RADIOLOGIA | O74: DIAGNOSR | P74: DIAGNOSR - CENTRO DEL DIAGNOSTICO | Q74: NO | R74: NNM | S74: 340209 | T74: RX RAQUIS-COLUMNA- 1 EXP. | U74: SIN REGION | V74: 1 | W74: VEIGA, SABRINA | X74: 0 | Y74: VARELA, JULIO | Z74: 0 | AA74: 0 | AB74: 0 | AC74: 0 | AD74: S/S | AE74: ELUCERO | AG74: 0 | AH74: 0.43958333 | AI74: 46148
A75: 995717 | B75: 46144 | C75: GONZALEZ, MARTA YOLANDA | D75: 86 | E75: F | F75: PAMI AMB CC | G75: 150156676201/00 | I75: Lista para Facturar | J75: Exento | K75: UNICO | L75: 1 | N75: RADIOLOGIA | O75: DIAGNOSR | P75: DIAGNOSR - CENTRO DEL DIAGNOSTICO | Q75: NO | R75: NNM | S75: 340210 | T75: RX RAQUIS-COLUMNA-EXP. SUBS. | U75: SIN REGION | V75: 1 | W75: VEIGA, SABRINA | X75: 0 | Y75: VARELA, JULIO | Z75: 0 | AA75: 0 | AB75: 0 | AC75: 0 | AD75: S/S | AE75: ELUCERO | AG75: 0 | AH75: 0.43958333 | AI75: 46148
A76: 995718 | B76: 46144 | C76: GORRI, SUSANA | D76: 74 | E76: F | F76: PAMI INT CC | G76: 150620286300/00 | I76: Lista para Facturar | J76: Exento | K76: UNICO | L76: 1 | N76: RADIOLOGIA | O76: DIAGNOSR | P76: CLINIC - CLINICA CIUDAD | Q76: NO | R76: NNM | S76: 340202 | T76: RX CRANEO CARA SENOS PAR.SUBS | U76: SIN REGION | V76: 1 | W76: SAT, MARIANA | X76: 0 | Y76: VARELA, JULIO | Z76: 0 | AA76: 0 | AB76: 0 | AC76: 0 | AD76: S/S | AE76: PMARTIN | AF76: Proceso Auto: Recalculo Orden | AG76: 0 | AH76: 0.44027778 | AI76: 46148
A77: 995718 | B77: 46144 | C77: GORRI, SUSANA | D77: 74 | E77: F | F77: PAMI INT CC | G77: 150620286300/00 | I77: Lista para Facturar | J77: Exento | K77: UNICO | L77: 1 | N77: RADIOLOGIA | O77: DIAGNOSR | P77: CLINIC - CLINICA CIUDAD | Q77: NO | R77: NNM | S77: 340201 | T77: RX CRANEO CARA SENOS PAR. 1EXP | U77: SIN REGION | V77: 1 | W77: SAT, MARIANA | X77: 0 | Y77: VARELA, JULIO | Z77: 0 | AA77: 0 | AB77: 0 | AC77: 0 | AD77: S/S | AE77: PMARTIN | AF77: Proceso Auto: Recalculo Orden | AG77: 0 | AH77: 0.44027778 | AI77: 46148
A78: 995719 | B78: 46144 | C78: CARVALLO, HILDA GRACIELA | D78: 64 | E78: F | F78: PAMI AMB CC | G78: 140107277107/00 | I78: Lista para Facturar | J78: Exento | K78: UNICO | L78: 1 | N78: RADIOLOGIA | O78: DIAGNOSR | P78: DIAGNOSR - CENTRO DEL DIAGNOSTICO | Q78: NO | R78: NNM | S78: 340210 | T78: RX RAQUIS-COLUMNA-EXP. SUBS. | U78: SIN REGION | V78: 1 | W78: OBLITAS, ROCIO | X78: 0 | Y78: VARELA, JULIO | Z78: 0 | AA78: 0 | AB78: 0 | AC78: 0 | AD78: S/S | AE78: ESLUCERO | AG78: 0 | AH78: 0.44027778 | AI78: 46148
A79: 995719 | B79: 46144 | C79: CARVALLO, HILDA GRACIELA | D79: 64 | E79: F | F79: PAMI AMB CC | G79: 140107277107/00 | I79: Lista para Facturar | J79: Exento | K79: UNICO | L79: 1 | N79: RADIOLOGIA | O79: DIAGNOSR | P79: DIAGNOSR - CENTRO DEL DIAGNOSTICO | Q79: NO | R79: NNM | S79: 340209 | T79: RX RAQUIS-COLUMNA- 1 EXP. | U79: SIN REGION | V79: 1 | W79: OBLITAS, ROCIO | X79: 0 | Y79: VARELA, JULIO | Z79: 0 | AA79: 0 | AB79: 0 | AC79: 0 | AD79: S/S | AE79: ESLUCERO | AG79: 0 | AH79: 0.44027778 | AI79: 46148
A80: 995720 | B80: 46144 | C80: GONZALEZ, MARTA YOLANDA | D80: 86 | E80: F | F80: PAMI AMB CC | G80: 150156676201/00 | I80: Pendiente | J80: Exento | K80: IMAGEN SALUD | L80: 2 | N80: DENSITOMETRIA | O80: DIAGNOSR | P80: DIAGNOSR - CENTRO DEL DIAGNOSTICO | Q80: NO | R80: NNM | S80: 341202 | T80: DENSITOMETRIA OSEA DOS O MAS R | U80: SIN REGION | V80: 1 | W80: VEIGA, SABRINA | X80: 0 | Y80: OBLITAS, ROCIO | Z80: 0 | AA80: 0 | AB80: 0 | AC80: 0 | AD80: S/S | AE80: ELUCERO | AF80: Trat.Prolongado: Consumos incompletos | AG80: 0 | AH80: 0.44097222 | AI80: 46148
A81: 995721 | B81: 46144 | C81: GOMEZ MELGARE, INES | D81: 40 | E81: F | F81: PARTICULAR CD | G81: 32145844 | I81: Lista para Facturar | J81: Exento | K81: UNICO | L81: 1 | N81: ODONTOLOGIA-2D | O81: DIAGNOSR | P81: DIAGNOSR - CENTRO DEL DIAGNOSTICO | Q81: NO | R81: NNM | S81: 333300 | T81: RX PANORAMICA DENTAL | U81: SIN REGION | V81: 1 | W81: SIN PEDIDO MEDICO, . | X81: 0 | Y81: FORESI, EMILIA | Z81: 0 | AA81: 0 | AB81: 0 | AC81: 0 | AD81: S/S | AE81: ELUCERO | AG81: 0 | AH81: 0.44236111 | AI81: 46148
A82: 995722 | B82: 46144 | C82: ARELLANO, HILDA | D82: 67 | E82: F | F82: PAMI AMB CC | G82: 140120104007/00 | I82: Lista para Facturar | J82: Exento | K82: UNICO | L82: 1 | N82: RADIOLOGIA | O82: DIAGNOSR | P82: DIAGNOSR - CENTRO DEL DIAGNOSTICO | Q82: NO | R82: NNM | S82: 340214 | T82: MED. COMPARATIVA DE M.I.XESTUD | U82: SIN REGION | V82: 1 | W82: SOSA AVILA, DIEGO | X82: 0 | Y82: ASIGNADO, POR RIS | Z82: 0 | AA82: 0 | AB82: 0 | AC82: 0 | AD82: S/S | AE82: ESLUCERO | AG82: 0 | AH82: 0.44305556 | AI82: 46148
A83: 995723 | B83: 46144 | C83: LOPEZ, JESUS ISMAEL | D83: 67 | E83: M | F83: H REGIONAL MG | G83: 12347182 | I83: Lista para Facturar | J83: Exento | K83: UNICO | L83: 1 | N83: TOMOGRAFIA | O83: DIAGNOSR | P83: MALARG - MALARGUE | Q83: NO | R83: NNM | S83: 922026 | T83: TOMOGRAFIA COMPUTADA MULTICORT | U83: SIN REGION | V83: 1 | W83: SOLER, BERNARDITA | X83: 0 | Y83: ASIGNADO, POR RIS | Z83: 0 | AA83: 0 | AB83: 0 | AC83: 0 | AD83: S/S | AE83: CIRIARTE | AG83: 0 | AH83: 0.44305556 | AI83: 46148
A84: 995724 | B84: 46144 | C84: HERNANDEZ, OSCAR ENRIQUE | D84: 79 | E84: M | F84: PAMI INT CC | G84: 15053970010600 | I84: Lista para Facturar | J84: Exento | K84: UNICO | L84: 1 | N84: RADIOLOGIA | O84: DIAGNOSR | P84: CLINIC - CLINICA CIUDAD | Q84: NO | R84: NNM | S84: 340301 | T84: RX DE TORAX | U84: SIN REGION | V84: 1 | W84: SAT, MARIANA | X84: 0 | Y84: VARELA, JULIO | Z84: 0 | AA84: 0 | AB84: 0 | AC84: 0 | AD84: S/S | AE84: PMARTIN | AF84: Proceso Auto: Recalculo Orden | AG84: 0 | AH84: 0.44791667 | AI84: 46148
A85: 995725 | B85: 46144 | C85: VILLAR, FLOR MARIA | D85: 72 | E85: M | F85: PAMI AMB CC | G85: 150637993501/00 | I85: Lista para Facturar | J85: Exento | K85: UNICO | L85: 1 | N85: RADIOLOGIA | O85: DIAGNOSR | P85: MALARG - MALARGUE | Q85: NO | R85: NNM | S85: 340213 | T85: RX CODO MANO PIE 2 X/PLACA 1EX | U85: SIN REGION | V85: 4 | W85: CARLEVARIS, LEANDRO | X85: 0 | Y85: VARELA, JULIO | Z85: 0 | AA85: 0 | AB85: 0 | AC85: 0 | AD85: S/S | AE85: LOJEDA | AG85: 0 | AH85: 0.46319444 | AI85: 46148
A86: 995726 | B86: 46144 | C86: VAZQUEZ, JOSE LUIS | D86: 68 | E86: M | F86: PAMI AMB CC | G86: 140127304604/00 | I86: Lista para Facturar | J86: Exento | K86: UNICO | L86: 1 | N86: RADIOLOGIA | O86: DIAGNOSR | P86: MALARG - MALARGUE | Q86: NO | R86: NNM | S86: 340213 | T86: RX CODO MANO PIE 2 X/PLACA 1EX | U86: SIN REGION | V86: 1 | W86: CASTILLO, CARLOS JORGE | X86: 0 | Y86: VARELA, JULIO | Z86: 0 | AA86: 0 | AB86: 0 | AC86: 0 | AD86: S/S | AE86: LOJEDA | AG86: 0 | AH86: 0.46388889 | AI86: 46148
A87: 995726 | B87: 46144 | C87: VAZQUEZ, JOSE LUIS | D87: 68 | E87: M | F87: PAMI AMB CC | G87: 140127304604/00 | I87: Lista para Facturar | J87: Exento | K87: UNICO | L87: 1 | N87: RADIOLOGIA | O87: DIAGNOSR | P87: MALARG - MALARGUE | Q87: NO | R87: NNM | S87: 340211 | T87: RX HOMBRO HUMERO PELVIS CADERA | U87: SIN REGION | V87: 1 | W87: CASTILLO, CARLOS JORGE | X87: 0 | Y87: VARELA, JULIO | Z87: 0 | AA87: 0 | AB87: 0 | AC87: 0 | AD87: S/S | AE87: LOJEDA | AG87: 0 | AH87: 0.46388889 | AI87: 46148
A88: 995727 | B88: 46144 | C88: CUELLO, JOSEFINA MERCEDES | D88: 68 | E88: F | F88: PAMI AMB CC | G88: 140026303403/00 | I88: Lista para Facturar | J88: Exento | K88: UNICO | L88: 1 | N88: RADIOLOGIA | O88: DIAGNOSR | P88: DIAGNOSR - CENTRO DEL DIAGNOSTICO | Q88: NO | R88: NNM | S88: 340209 | T88: RX RAQUIS-COLUMNA- 1 EXP. | U88: SIN REGION | V88: 1 | W88: CUELLO, ISIDRO | X88: 0 | Y88: VARELA, JULIO | Z88: 0 | AA88: 0 | AB88: 0 | AC88: 0 | AD88: S/S | AE88: ELUCERO | AG88: 0 | AH88: 0.46597222 | AI88: 46148
A89: 995727 | B89: 46144 | C89: CUELLO, JOSEFINA MERCEDES | D89: 68 | E89: F | F89: PAMI AMB CC | G89: 140026303403/00 | I89: Lista para Facturar | J89: Exento | K89: UNICO | L89: 1 | N89: RADIOLOGIA | O89: DIAGNOSR | P89: DIAGNOSR - CENTRO DEL DIAGNOSTICO | Q89: NO | R89: NNM | S89: 340210 | T89: RX RAQUIS-COLUMNA-EXP. SUBS. | U89: SIN REGION | V89: 1 | W89: CUELLO, ISIDRO | X89: 0 | Y89: VARELA, JULIO | Z89: 0 | AA89: 0 | AB89: 0 | AC89: 0 | AD89: S/S | AE89: ELUCERO | AG89: 0 | AH89: 0.46597222 | AI89: 46148
A90: 995727 | B90: 46144 | C90: CUELLO, JOSEFINA MERCEDES | D90: 68 | E90: F | F90: PAMI AMB CC | G90: 140026303403/00 | I90: Lista para Facturar | J90: Exento | K90: UNICO | L90: 1 | N90: RADIOLOGIA | O90: DIAGNOSR | P90: DIAGNOSR - CENTRO DEL DIAGNOSTICO | Q90: NO | R90: NNM | S90: 340211 | T90: RX HOMBRO HUMERO PELVIS CADERA | U90: SIN REGION | V90: 1 | W90: CUELLO, ISIDRO | X90: 0 | Y90: VARELA, JULIO | Z90: 0 | AA90: 0 | AB90: 0 | AC90: 0 | AD90: S/S | AE90: ELUCERO | AG90: 0 | AH90: 0.46597222 | AI90: 46148
A91: 995728 | B91: 46144 | C91: RETAMALES, INES DEL CARMEN | D91: 71 | E91: F | F91: PARTICULAR CD | I91: Lista para Facturar | J91: Exento | K91: UNICO | L91: 1 | N91: TOMOGRAFIA | O91: DIAGNOSR | P91: DIAGNOSR - CENTRO DEL DIAGNOSTICO | Q91: NO | R91: NNM | S91: 341001 | T91: TOMOGRAFIA COMPUTADA CEREBRAL | U91: SIN REGION | V91: 1 | W91: CONSELMO, MARIANA | X91: 0 | Y91: ASIGNADO, POR RIS | Z91: 2200 | AA91: 0 | AB91: 0 | AC91: 0 | AD91: S/S | AE91: ESLUCERO | AG91: 2200 | AH91: 0.46944444 | AI91: 46148
A92: 995729 | B92: 46144 | C92: ARACENA, ESTELA EDITH | D92: 64 | E92: F | F92: PAMI AMB CC | G92: 140089320800/00 | I92: Lista para Facturar | J92: Exento | K92: UNICO | L92: 1 | N92: RADIOLOGIA | O92: DIAGNOSR | P92: MALARG - MALARGUE | Q92: NO | R92: NNM | S92: 340213 | T92: RX CODO MANO PIE 2 X/PLACA 1EX | U92: SIN REGION | V92: 2 | W92: CUELLO, ISIDRO | X92: 0 | Y92: VARELA, JULIO | Z92: 0 | AA92: 0 | AB92: 0 | AC92: 0 | AD92: S/S | AE92: LOJEDA | AG92: 0 | AH92: 0.47083333 | AI92: 46148
A93: 995730 | B93: 46144 | C93: VARELA, JULIO | D93: 78 | E93: M | F93: PAMI AMB CC | G93: 150584523700/00 | I93: Lista para Facturar | J93: Exento | K93: UNICO | L93: 1 | N93: TOMOGRAFIA | O93: DIAGNOSR | P93: DIAGNOSR - CENTRO DEL DIAGNOSTICO | Q93: NO | R93: NNM | S93: 341010 | T93: TOMOGRAFIA COMPUTADA TORACICA | U93: SIN REGION | V93: 1 | W93: SIN PEDIDO MEDICO, . | X93: 0 | Y93: ASIGNADO, POR RIS | Z93: 0 | AA93: 0 | AB93: 0 | AC93: 0 | AD93: S/S | AE93: ELUCERO | AG93: 0 | AH93: 0.47152778 | AI93: 46148
A94: 995731 | B94: 46144 | C94: MUÑOZ, CLAUDIA ELIZABETH | D94: 41 | E94: F | F94: SANCOR SALUD | G94: 2111148/01 | I94: Lista para Facturar | J94: Exento | K94: 2/0 RX-TAC-ECO | L94: 2 | N94: RADIOLOGIA | O94: DIAGNOSR | P94: MALARG - MALARGUE | Q94: NO | R94: NNM | S94: 340301 | T94: RX DE TORAX | U94: SIN REGION | V94: 1 | W94: NIELSEN, CARINA | X94: 0 | Y94: VARELA, JULIO | Z94: 0 | AA94: 0 | AB94: 0 | AC94: 0 | AD94: S/S | AE94: LOJEDA | AG94: 0 | AH94: 0.47152778 | AI94: 46148
A95: 995731 | B95: 46144 | C95: MUÑOZ, CLAUDIA ELIZABETH | D95: 41 | E95: F | F95: SANCOR SALUD | G95: 2111148/01 | I95: Lista para Facturar | J95: Exento | K95: 2/0 RX-TAC-ECO | L95: 2 | N95: RADIOLOGIA | O95: DIAGNOSR | P95: MALARG - MALARGUE | Q95: NO | R95: NNM | S95: 340302 | T95: RX TORAX EXP. SUBS. | U95: SIN REGION | V95: 1 | W95: NIELSEN, CARINA | X95: 0 | Y95: VARELA, JULIO | Z95: 0 | AA95: 0 | AB95: 0 | AC95: 0 | AD95: S/S | AE95: LOJEDA | AG95: 0 | AH95: 0.47152778 | AI95: 46148
A96: 995732 | B96: 46144 | C96: GIACCONI GUEVARA, LUDMILA AGOSTINA | D96: 16 | E96: F | F96: SANCOR SALUD | G96: 2105678/04 | I96: Lista para Facturar | J96: Exento | K96: 2/0 RX-TAC-ECO | L96: 2 | N96: RADIOLOGIA | O96: DIAGNOSR | P96: MALARG - MALARGUE | Q96: NO | R96: NNM | S96: 340213 | T96: RX CODO MANO PIE 2 X/PLACA 1EX | U96: SIN REGION | V96: 4 | W96: PONCE, LEANDRO | X96: 0 | Y96: VARELA, JULIO | Z96: 0 | AA96: 0 | AB96: 0 | AC96: 0 | AD96: S/S | AE96: LOJEDA | AG96: 0 | AH96: 0.47361111 | AI96: 46148
A97: 995733 | B97: 46144 | C97: SANCHEZ, CEFERINA | D97: 81 | E97: F | F97: PAMI AMB CC | G97: 155907547803/00 | I97: Lista para Facturar | J97: Exento | K97: UNICO | L97: 1 | N97: RADIOLOGIA | O97: DIAGNOSR | P97: MALARG - MALARGUE | Q97: NO | R97: NNM | S97: 340209 | T97: RX RAQUIS-COLUMNA- 1 EXP. | U97: SIN REGION | V97: 1 | W97: CUELLO, ISIDRO | X97: 0 | Y97: VARELA, JULIO | Z97: 0 | AA97: 0 | AB97: 0 | AC97: 0 | AD97: S/S | AE97: LOJEDA | AG97: 0 | AH97: 0.47569444 | AI97: 46148
A98: 995733 | B98: 46144 | C98: SANCHEZ, CEFERINA | D98: 81 | E98: F | F98: PAMI AMB CC | G98: 155907547803/00 | I98: Lista para Facturar | J98: Exento | K98: UNICO | L98: 1 | N98: RADIOLOGIA | O98: DIAGNOSR | P98: MALARG - MALARGUE | Q98: NO | R98: NNM | S98: 340213 | T98: RX CODO MANO PIE 2 X/PLACA 1EX | U98: SIN REGION | V98: 1 | W98: CUELLO, ISIDRO | X98: 0 | Y98: VARELA, JULIO | Z98: 0 | AA98: 0 | AB98: 0 | AC98: 0 | AD98: S/S | AE98: LOJEDA | AG98: 0 | AH98: 0.47569444 | AI98: 46148
A99: 995733 | B99: 46144 | C99: SANCHEZ, CEFERINA | D99: 81 | E99: F | F99: PAMI AMB CC | G99: 155907547803/00 | I99: Lista para Facturar | J99: Exento | K99: UNICO | L99: 1 | N99: RADIOLOGIA | O99: DIAGNOSR | P99: MALARG - MALARGUE | Q99: NO | R99: NNM | S99: 340210 | T99: RX RAQUIS-COLUMNA-EXP. SUBS. | U99: SIN REGION | V99: 1 | W99: CUELLO, ISIDRO | X99: 0 | Y99: VARELA, JULIO | Z99: 0 | AA99: 0 | AB99: 0 | AC99: 0 | AD99: S/S | AE99: LOJEDA | AG99: 0 | AH99: 0.47569444 | AI99: 46148
A100: 995734 | B100: 46144 | C100: PAVEZ, GUSTAVO FABIAN | D100: 52 | E100: M | F100: PAMI AMB CC | G100: 155570484609/00 | I100: Lista para Facturar | J100: Exento | K100: UNICO | L100: 1 | N100: RADIOLOGIA | O100: DIAGNOSR | P100: CLINIC - CLINICA CIUDAD | Q100: NO | R100: NNM | S100: 340301 | T100: RX DE TORAX | U100: SIN REGION | V100: 1 | W100: GOMEZ, SARA | X100: 0 | Y100: VARELA, JULIO | Z100: 0 | AA100: 0 | AB100: 0 | AC100: 0 | AD100: S/S | AE100: PMARTIN | AG100: 0 | AH100: 0.48541667 | AI100: 46148
A101: 995734 | B101: 46144 | C101: PAVEZ, GUSTAVO FABIAN | D101: 52 | E101: M | F101: PAMI AMB CC | G101: 155570484609/00 | I101: Lista para Facturar | J101: Exento | K101: UNICO | L101: 1 | N101: RADIOLOGIA | O101: DIAGNOSR | P101: CLINIC - CLINICA CIUDAD | Q101: NO | R101: NNM | S101: 340302 | T101: RX TORAX EXP. SUBS. | U101: SIN REGION | V101: 1 | W101: GOMEZ, SARA | X101: 0 | Y101: VARELA, JULIO | Z101: 0 | AA101: 0 | AB101: 0 | AC101: 0 | AD101: S/S | AE101: PMARTIN | AG101: 0 | AH101: 0.48541667 | AI101: 46148
A102: 995735 | B102: 46144 | C102: OLMOS, BENICIO JOAQUIN | D102: 10 | E102: M | F102: SANCOR SALUD | G102: 2108360/04 | I102: Lista para Facturar | J102: Exento | K102: 2/0 RX-TAC-ECO | L102: 2 | N102: RADIOLOGIA | O102: DIAGNOSR | P102: MALARG - MALARGUE | Q102: NO | R102: NNM | S102: 340301 | T102: RX DE TORAX | U102: SIN REGION | V102: 1 | W102: NIELSEN, CARINA | X102: 0 | Y102: VARELA, JULIO | Z102: 0 | AA102: 0 | AB102: 0 | AC102: 0 | AD102: S/S | AE102: LOJEDA | AG102: 0 | AH102: 0.51111111 | AI102: 46148
A103: 995735 | B103: 46144 | C103: OLMOS, BENICIO JOAQUIN | D103: 10 | E103: M | F103: SANCOR SALUD | G103: 2108360/04 | I103: Lista para Facturar | J103: Exento | K103: 2/0 RX-TAC-ECO | L103: 2 | N103: RADIOLOGIA | O103: DIAGNOSR | P103: MALARG - MALARGUE | Q103: NO | R103: NNM | S103: 340302 | T103: RX TORAX EXP. SUBS. | U103: SIN REGION | V103: 1 | W103: NIELSEN, CARINA | X103: 0 | Y103: VARELA, JULIO | Z103: 0 | AA103: 0 | AB103: 0 | AC103: 0 | AD103: S/S | AE103: LOJEDA | AG103: 0 | AH103: 0.51111111 | AI103: 46148
...

Sheet DERIVANTES
A1: ID | B1: DERIVANTE | C1: MAT | D1: PROPIO/EXTERNO | E1: PISO | F1: SIN ESPACIOS
A2: 5 | B2: SCHIAVONE, JULIO | C2: 11079 | D2: =IF(B2="","",IFERROR(VLOOKUP(B2,'DERIVANTES PROPIOS'!A:D,2,FALSE),"RESTO")) -> RESTO | E2: =IF(B2="","",IFERROR(VLOOKUP(B2,'DERIVANTES PROPIOS'!A:D,3,FALSE),"RESTO")) -> RESTO | F2: =+TRIM(B2) -> SCHIAVONE, JULIO
A3: 6 | B3: CERRUTI, FAUSTO | C3: 8285 | D3: =IF(B3="","",IFERROR(VLOOKUP(B3,'DERIVANTES PROPIOS'!A:D,2,FALSE),"RESTO")) -> RESTO | E3: =IF(B3="","",IFERROR(VLOOKUP(B3,'DERIVANTES PROPIOS'!A:D,3,FALSE),"RESTO")) -> RESTO | F3: =+TRIM(B3) -> CERRUTI, FAUSTO
A4: 8 | B4: SCHIAVONE, LEONARDO | C4: 11080 | D4: =IF(B4="","",IFERROR(VLOOKUP(B4,'DERIVANTES PROPIOS'!A:D,2,FALSE),"RESTO")) -> RESTO | E4: =IF(B4="","",IFERROR(VLOOKUP(B4,'DERIVANTES PROPIOS'!A:D,3,FALSE),"RESTO")) -> RESTO | F4: =+TRIM(B4) -> SCHIAVONE, LEONARDO
A5: 9 | B5: CASADO, HEBE SILVINA | C5: 8203 | D5: =IF(B5="","",IFERROR(VLOOKUP(B5,'DERIVANTES PROPIOS'!A:D,2,FALSE),"RESTO")) -> RESTO | E5: =IF(B5="","",IFERROR(VLOOKUP(B5,'DERIVANTES PROPIOS'!A:D,3,FALSE),"RESTO")) -> RESTO | F5: =+TRIM(B5) -> CASADO, HEBE SILVINA
A6: 10 | B6: GOMILA, JORGE | C6: 9149 | D6: =IF(B6="","",IFERROR(VLOOKUP(B6,'DERIVANTES PROPIOS'!A:D,2,FALSE),"RESTO")) -> RESTO | E6: =IF(B6="","",IFERROR(VLOOKUP(B6,'DERIVANTES PROPIOS'!A:D,3,FALSE),"RESTO")) -> RESTO | F6: =+TRIM(B6) -> GOMILA, JORGE
A7: 11 | B7: NOMI, MARIA DEL CARMEN | C7: 10188 | D7: =IF(B7="","",IFERROR(VLOOKUP(B7,'DERIVANTES PROPIOS'!A:D,2,FALSE),"RESTO")) -> RESTO | E7: =IF(B7="","",IFERROR(VLOOKUP(B7,'DERIVANTES PROPIOS'!A:D,3,FALSE),"RESTO")) -> RESTO | F7: =+TRIM(B7) -> NOMI, MARIA DEL CARMEN
A8: 12 | B8: BOROVINA, ALDO | C8: 7996 | D8: =IF(B8="","",IFERROR(VLOOKUP(B8,'DERIVANTES PROPIOS'!A:D,2,FALSE),"RESTO")) -> RESTO | E8: =IF(B8="","",IFERROR(VLOOKUP(B8,'DERIVANTES PROPIOS'!A:D,3,FALSE),"RESTO")) -> RESTO | F8: =+TRIM(B8) -> BOROVINA, ALDO
A9: 13 | B9: MUDCHELLA, OSCAR | C9: 10063 | D9: =IF(B9="","",IFERROR(VLOOKUP(B9,'DERIVANTES PROPIOS'!A:D,2,FALSE),"RESTO")) -> RESTO | E9: =IF(B9="","",IFERROR(VLOOKUP(B9,'DERIVANTES PROPIOS'!A:D,3,FALSE),"RESTO")) -> RESTO | F9: =+TRIM(B9) -> MUDCHELLA, OSCAR
A10: 14 | B10: FRANCISCO, MARIA | C10: 8875 | D10: =IF(B10="","",IFERROR(VLOOKUP(B10,'DERIVANTES PROPIOS'!A:D,2,FALSE),"RESTO")) -> RESTO | E10: =IF(B10="","",IFERROR(VLOOKUP(B10,'DERIVANTES PROPIOS'!A:D,3,FALSE),"RESTO")) -> RESTO | F10: =+TRIM(B10) -> FRANCISCO, MARIA
A11: 15 | B11: PEREZ, ROBERTO | C11: 10431 | D11: =IF(B11="","",IFERROR(VLOOKUP(B11,'DERIVANTES PROPIOS'!A:D,2,FALSE),"RESTO")) -> RESTO | E11: =IF(B11="","",IFERROR(VLOOKUP(B11,'DERIVANTES PROPIOS'!A:D,3,FALSE),"RESTO")) -> RESTO | F11: =+TRIM(B11) -> PEREZ, ROBERTO
A12: 16 | B12: BOROVINA, ANA | C12: 7997 | D12: =IF(B12="","",IFERROR(VLOOKUP(B12,'DERIVANTES PROPIOS'!A:D,2,FALSE),"RESTO")) -> RESTO | E12: =IF(B12="","",IFERROR(VLOOKUP(B12,'DERIVANTES PROPIOS'!A:D,3,FALSE),"RESTO")) -> RESTO | F12: =+TRIM(B12) -> BOROVINA, ANA
A13: 17 | B13: CERRUTI, JUAN CARLOS | C13: 8286 | D13: =IF(B13="","",IFERROR(VLOOKUP(B13,'DERIVANTES PROPIOS'!A:D,2,FALSE),"RESTO")) -> RESTO | E13: =IF(B13="","",IFERROR(VLOOKUP(B13,'DERIVANTES PROPIOS'!A:D,3,FALSE),"RESTO")) -> RESTO | F13: =+TRIM(B13) -> CERRUTI, JUAN CARLOS
... A4271: 4338 | B4271: MARCELO, JORGE | C4271: 1658 | D4271: =IF(B4271="","",IFERROR(VLOOKUP(B4271,'DERIVANTES PROPIOS'!A:D,2,FALSE),"RESTO")) -> RESTO | E4271: =IF(B4271="","",IFERROR(VLOOKUP(B4271,'DERIVANTES PROPIOS'!A:D,3,FALSE),"RESTO")) -> RESTO | F4271: =+TRIM(B4271) -> MARCELO, JORGE

Sheet DERIVANTES PROPIOS
A1: APELLIDO NOMBRE | B1: PROPIO/EXTERNO | C1: PISO
A2: BITTAR GARCIA, CARLOS | B2: PROPIO | C2: PISO1
A3: BLANCO ALLEMANT, ALEJANDRA | B3: PROPIO | C3: PISO1
A4: CABAÑA, R JAVIER | B4: PROPIO | C4: PISO1
A5: CRUZ PEREZ, INES | B5: PROPIO | C5: PISO1
A6: FORNARA, CRISTIAN | B6: PROPIO | C6: PISO1
A7: GERARDI, FRANCISCO JAVIER | B7: PROPIO | C7: PISO1
A8: MARTINEZ, ANTONELLA | B8: PROPIO | C8: PISO1
A9: ANTONINI, GUSTAVO | B9: PROPIO | C9: PISO2
A10: CAMILLETTI, MARIANO | B10: PROPIO | C10: PISO2
A11: CARLEVARIS, LEANDRO | B11: PROPIO | C11: PISO2
A12: CHAVARRI, EDUARDO | B12: PROPIO | C12: PISO2
... A39: SIN PEDIDO MEDICO, . | B39: SIN PEDIDO MEDICO | C39: RESTO

Sheet SERVICIOS
A1: DENSITOMETRIA
A2: ECO DOPPLER COLOR
A3: ECOCARDIOGRAMA
A4: ECOGRAFIA
A5: ELECTROCARDIOGRAMA
A6: MAMOGRAFIA
A7: ODONTOLOGIA-2D
A8: ODONTOLOGIA-3D
A9: RADIOLOGIA
A10: RESONANCIA
A11: TOMOGRAFIA
